gdtesttask
