Metadata-Version: 1.0
Name: gdtesttask
Version: 1.0.1
Summary: Simple python project for jenkins task
Home-page: https://github.com/shev2dev/jenkins-test
Author: Shevchenko Artem
Author-email: shevchenkoaa@sgu.ru
License: MIT
Keywords: test jenkins easy
Platform: UNKNOWN
